narwhals/__init__.py
narwhals/_expression_parsing.py
narwhals/dataframe.py
narwhals/dependencies.py
narwhals/dtypes.py
narwhals/exceptions.py
narwhals/expr.py
narwhals/functions.py
narwhals/group_by.py
narwhals/py.typed
narwhals/schema.py
narwhals/selectors.py
narwhals/series.py
narwhals/this.py
narwhals/translate.py
narwhals/typing.py
narwhals/utils.py
narwhals/_arrow/__init__.py
narwhals/_arrow/dataframe.py
narwhals/_arrow/expr.py
narwhals/_arrow/group_by.py
narwhals/_arrow/namespace.py
narwhals/_arrow/selectors.py
narwhals/_arrow/series.py
narwhals/_arrow/typing.py
narwhals/_arrow/utils.py
narwhals/_dask/__init__.py
narwhals/_dask/dataframe.py
narwhals/_dask/expr.py
narwhals/_dask/group_by.py
narwhals/_dask/namespace.py
narwhals/_dask/selectors.py
narwhals/_dask/typing.py
narwhals/_dask/utils.py
narwhals/_duckdb/__init__.py
narwhals/_duckdb/dataframe.py
narwhals/_duckdb/series.py
narwhals/_ibis/__init__.py
narwhals/_ibis/dataframe.py
narwhals/_ibis/series.py
narwhals/_interchange/__init__.py
narwhals/_interchange/dataframe.py
narwhals/_interchange/series.py
narwhals/_pandas_like/__init__.py
narwhals/_pandas_like/dataframe.py
narwhals/_pandas_like/expr.py
narwhals/_pandas_like/group_by.py
narwhals/_pandas_like/namespace.py
narwhals/_pandas_like/selectors.py
narwhals/_pandas_like/series.py
narwhals/_pandas_like/typing.py
narwhals/_pandas_like/utils.py
narwhals/_polars/__init__.py
narwhals/_polars/dataframe.py
narwhals/_polars/expr.py
narwhals/_polars/group_by.py
narwhals/_polars/namespace.py
narwhals/_polars/series.py
narwhals/_polars/typing.py
narwhals/_polars/utils.py
narwhals/_spark_like/__init__.py
narwhals/_spark_like/dataframe.py
narwhals/_spark_like/expr.py
narwhals/_spark_like/group_by.py
narwhals/_spark_like/namespace.py
narwhals/_spark_like/typing.py
narwhals/_spark_like/utils.py
narwhals/stable/__init__.py
narwhals/stable/v1/__init__.py
narwhals/stable/v1/_dtypes.py
narwhals/stable/v1/dependencies.py
narwhals/stable/v1/dtypes.py
narwhals-1.18.1.dist-info/METADATA
narwhals-1.18.1.dist-info/WHEEL
narwhals-1.18.1.dist-info/licenses/LICENSE.md
narwhals-1.18.1.dist-info/RECORD
