Metadata-Version: 2.3
Name: narwhals
Version: 1.18.1
Summary: Extremely lightweight compatibility layer between dataframe libraries
Project-URL: Homepage, https://github.com/narwhals-dev/narwhals
Project-URL: Bug Tracker, https://github.com/narwhals-dev/narwhals
Author-email: Marco Gorelli <33491632+MarcoGorelli@users.noreply.github.com>
Classifier: License :: OSI Approved :: MIT License
Classifier: Operating System :: OS Independent
Classifier: Programming Language :: Python :: 3
Requires-Python: >=3.8
Provides-Extra: cudf
Requires-Dist: cudf>=23.08.00; extra == 'cudf'
Provides-Extra: dask
Requires-Dist: dask[dataframe]>=2024.7; extra == 'dask'
Provides-Extra: modin
Requires-Dist: modin; extra == 'modin'
Provides-Extra: pandas
Requires-Dist: pandas>=0.25.3; extra == 'pandas'
Provides-Extra: polars
Requires-Dist: polars>=0.20.3; extra == 'polars'
Provides-Extra: pyarrow
Requires-Dist: pyarrow>=11.0.0; extra == 'pyarrow'
Provides-Extra: pyspark
Requires-Dist: pyspark>=3.3.0; extra == 'pyspark'
